pixelator/__init__.py
pixelator/pixelator.py
pixelator-1.3.0.dist-info/LICENSE
pixelator-1.3.0.dist-info/METADATA
pixelator-1.3.0.dist-info/WHEEL
pixelator-1.3.0.dist-info/top_level.txt
pixelator-1.3.0.dist-info/RECORD
