Metadata-Version: 2.2
Name: pixelator
Version: 1.3.0
Summary: Pixelate images to a specified size and color palette for AI/ML and various other purposes
Author-email: Connor Makowski <conmak@mit.edu>
Project-URL: Homepage, https://github.com/connor-makowski/pixelator
Project-URL: Bug Tracker, https://github.com/connor-makowski/pixelator/issues
Project-URL: Documentation, https://connor-makowski.github.io/pixelator/pixelator/pixelator.html
Classifier: Programming Language :: Python :: 3
Classifier: License :: OSI Approved :: MIT License
Classifier: Operating System :: OS Independent
Requires-Python: >=3.7
License-File: LICENSE
Requires-Dist: opencv-python>=4.11.0.86
Requires-Dist: type_enforced>=1.2.0
